{
	"class" : {
		"forField:basedOn:" : "TorstenBergmann 1/15/2015 17:51" },
	"instance" : {
		"addToTargetFields:" : "guest 10/13/2015 19:31",
		"asExpressionJoiningSource:toTarget:" : "guest 10/13/2015 19:31",
		"base" : "guest 10/13/2015 19:31",
		"canBind" : "guest 10/13/2015 19:31",
		"canHaveBase" : "guest 10/13/2015 19:31",
		"convertedDbValueOf:" : "guest 10/13/2015 19:31",
		"do:skipping:" : "guest 10/13/2015 19:31",
		"field" : "guest 10/13/2015 19:31",
		"field:base:" : "guest 10/13/2015 19:31",
		"get:withArguments:" : "guest 10/13/2015 19:31",
		"getMapping:named:" : "guest 10/13/2015 19:31",
		"printOn:" : "guest 10/13/2015 19:31",
		"printOnlySelfOn:" : "guest 10/13/2015 19:31",
		"printSQLOn:withParameters:" : "guest 10/13/2015 19:31",
		"printTreeOn:" : "guest 10/13/2015 19:31",
		"queryLevelBaseExpression" : "guest 10/13/2015 19:31",
		"rebuildOn:startingFrom:withOuterScopeBase:" : "guest 10/13/2015 19:31",
		"ultimateBaseExpression" : "guest 10/13/2015 19:31",
		"valueIn:" : "guest 10/13/2015 19:31" } }
