{
	"class" : {
		"named:basedOn:withArguments:" : "TorstenBergmann 1/15/2015 17:51" },
	"instance" : {
		"addBoundExpressionsIn:to:" : "guest 10/13/2015 19:31",
		"additionalExpressions" : "guest 10/13/2015 19:31",
		"allSourceFields" : "guest 10/13/2015 19:31",
		"allTargetFields" : "guest 10/13/2015 19:31",
		"asExpressionJoiningSource:toTarget:" : "guest 10/13/2015 19:31",
		"asField" : "guest 10/13/2015 19:31",
		"asGeneralGlorpExpression" : "guest 10/13/2015 19:31",
		"asGeneralGlorpExpressionWithFields" : "guest 10/13/2015 19:31",
		"asIndependentJoins" : "guest 10/13/2015 19:31",
		"asJoin" : "guest 10/13/2015 19:31",
		"assembleCompositePrimaryKeyFrom:and:" : "guest 10/13/2015 19:31",
		"beOuterJoin" : "guest 10/13/2015 19:31",
		"bindingIn:" : "guest 10/13/2015 19:31",
		"bindingType" : "guest 10/13/2015 19:31",
		"canHaveBase" : "guest 10/13/2015 19:31",
		"canUseBinding" : "guest 10/13/2015 19:31",
		"condenseBooleanEquality" : "guest 10/13/2015 19:31",
		"condenseBooleanEqualityExpressions" : "guest 10/13/2015 19:31",
		"condensePrimaryKeyComparison" : "guest 10/13/2015 19:31",
		"condensePrimaryKeyComparisons" : "guest 10/13/2015 19:31",
		"convertValueOf:in:" : "guest 10/13/2015 19:31",
		"convertedDbValueOf:" : "guest 10/13/2015 19:31",
		"createFor:withBase:symbol:" : "guest 10/13/2015 19:31",
		"do:skipping:" : "guest 10/13/2015 19:31",
		"expectsCollectionArgument" : "guest 10/13/2015 19:31",
		"generalExpressionPart" : "guest 10/13/2015 19:31",
		"get:withArguments:" : "guest 10/13/2015 19:31",
		"hasBindableExpressionsIn:" : "guest 10/13/2015 19:31",
		"isOuterJoin" : "guest 10/13/2015 19:31",
		"leftChild" : "guest 10/13/2015 19:31",
		"leftChild:" : "guest 10/13/2015 19:31",
		"mappableSourceFieldsDo:" : "guest 10/13/2015 19:31",
		"mappedFields" : "guest 10/13/2015 19:31",
		"named:basedOn:withArguments:" : "guest 10/13/2015 19:31",
		"operationFor:" : "",
		"outerJoin" : "guest 10/13/2015 19:31",
		"outerJoin:" : "guest 10/13/2015 19:31",
		"primaryKeyFromDictionary:" : "guest 10/13/2015 19:31",
		"printBasicSQLOn:withParameters:" : "guest 10/13/2015 19:31",
		"printBasicUnqualifiedSQLOn:withParameters:" : "guest 10/13/2015 19:31",
		"printComparisonTo:withParameters:on:" : "guest 10/13/2015 19:31",
		"printForANSIJoinTo:on:" : "guest 10/13/2015 19:31",
		"printMicrosoftOuterJoinOn:" : "guest 10/13/2015 19:31",
		"printOnlySelfOn:" : "guest 10/13/2015 19:31",
		"printOracleOuterJoinOn:" : "guest 10/13/2015 19:31",
		"printRelationOn:" : "guest 10/13/2015 19:31",
		"printSQLOn:withParameters:" : "guest 10/13/2015 19:31",
		"printSelectSQLOn:withParameters:" : "guest 10/13/2015 19:31",
		"printSimpleValueComparisonTo:on:" : "guest 10/13/2015 19:31",
		"printTreeOn:" : "guest 10/13/2015 19:31",
		"printUnqualifiedComparisonTo:withParameters:on:" : "guest 10/13/2015 19:31",
		"printUnqualifiedSQLOn:withParameters:" : "guest 10/13/2015 19:31",
		"printValue:on:" : "guest 10/13/2015 19:31",
		"printWithNullOn:" : "guest 10/13/2015 19:31",
		"queryLevelBaseExpression" : "guest 10/13/2015 19:31",
		"rebuildOn:startingFrom:withOuterScopeBase:" : "guest 10/13/2015 19:31",
		"relation" : "guest 10/13/2015 19:31",
		"relation:" : "guest 10/13/2015 19:31",
		"relationsWithCollectionArguments" : "guest 10/13/2015 19:31",
		"removeNonJoinParts" : "guest 10/13/2015 19:31",
		"replaceJoinsWithInverse" : "guest 10/13/2015 19:31",
		"rewriteEquality" : "guest 10/13/2015 19:31",
		"rewriteEqualityExpressions" : "guest 10/13/2015 19:31",
		"rewriteFunctionArguments" : "guest 10/13/2015 19:31",
		"rightChild" : "guest 10/13/2015 19:31",
		"rightChild:" : "guest 10/13/2015 19:31",
		"rightChildToRebuild" : "guest 10/13/2015 19:31",
		"shortCircuitOnNullComparison:" : "guest 10/13/2015 19:31",
		"sourceForTarget:" : "guest 10/13/2015 19:31",
		"tableToJoinFrom:" : "guest 10/13/2015 19:31",
		"tablesForANSIJoin" : "guest 10/13/2015 19:31",
		"targetKeys" : "guest 10/13/2015 19:31",
		"type" : "guest 10/13/2015 19:31",
		"ultimateBaseExpression" : "guest 10/13/2015 19:31",
		"useBindingFor:to:in:" : "guest 10/13/2015 19:31",
		"valueInBuilder:" : "guest 10/13/2015 19:31" } }
