{
	"class" : {
		"new" : "guest 10/21/2015 03:17",
		"newFor:in:" : "guest 10/21/2015 03:17" },
	"instance" : {
		"at:ifAbsent:" : "guest 10/13/2015 19:31",
		"at:ifAbsentPut:" : "guest 10/13/2015 19:31",
		"basicAt:ifAbsent:" : "guest 10/13/2015 19:31",
		"cachePolicy" : "guest 10/13/2015 19:31",
		"cachePolicy:" : "guest 10/13/2015 19:31",
		"do:" : "guest 10/13/2015 19:31",
		"expireAll" : "guest 10/13/2015 19:31",
		"expireKey:ifAbsent:" : "guest 10/13/2015 19:31",
		"expiredInstanceFor:" : "guest 10/13/2015 19:31",
		"hasExpired:" : "guest 10/13/2015 19:31",
		"hasItemExpired:" : "guest 10/13/2015 19:31",
		"includesKey:" : "guest 10/13/2015 19:31",
		"includesKey:as:" : "guest 10/13/2015 19:31",
		"includesKey:withClass:" : "guest 10/13/2015 19:31",
		"initialize" : "guest 10/13/2015 19:31",
		"initializeCache" : "guest 10/13/2015 19:31",
		"mainCache" : "guest 10/13/2015 19:31",
		"mainCache:" : "guest 10/13/2015 19:31",
		"markAsCurrentAtKey:" : "guest 10/13/2015 19:31",
		"markEntryAsCurrent:" : "guest 10/13/2015 19:31",
		"mournKeyOf:" : "guest 10/13/2015 19:31",
		"numberOfElements" : "guest 10/13/2015 19:31",
		"release" : "guest 10/13/2015 19:31",
		"removeKey:ifAbsent:" : "guest 10/13/2015 19:31",
		"session" : "guest 10/13/2015 19:31",
		"willRemoveItems" : "guest 10/13/2015 19:31" } }
